Kyandle/__init__.py
Kyandle/parsing/__init__.py
Kyandle/parsing/parser.py
Kyandle/serializing/__init__.py
Kyandle/serializing/serializer.py
Kyandle/utils/__init__.py
Kyandle/utils/errors.py
Kyandle/utils/exts.py
Kyandle-1.0.1.dist-info/License.md
Kyandle-1.0.1.dist-info/METADATA
Kyandle-1.0.1.dist-info/WHEEL
Kyandle-1.0.1.dist-info/top_level.txt
Kyandle-1.0.1.dist-info/RECORD
