Metadata-Version: 2.1
Name: Kyandle
Version: 1.0.1
Summary: Parser for the Kyandle (.kya) syntax
Home-page: https://github.com/Kyando2/candle
Author: Kyando
Author-email: amehikoji@gmail.com
License: UNKNOWN
Platform: UNKNOWN
Classifier: Programming Language :: Python :: 3
Classifier: License :: OSI Approved :: MIT License
Classifier: Operating System :: OS Independent
Requires-Python: >=3.6
